<?xml version='1.0' encoding='UTF-8'?>
<?compositeArtifactRepository version='1.0.0'?>
<repository name='&quot;Rosetta Repository&quot; 2.x' type='org.eclipse.equinox.internal.p2.artifact.repository.CompositeArtifactRepository' version='1.0.0'>
  <properties size='2'>
    <property name='p2.timestamp' value='1720553758376'/>
    <property name='p2.atomic.composite.loading' value='false'/>
  </properties>
  <children size='8'>
    <child location='2.0.x'/>
    <child location='2.1.x'/>
    <child location='2.2.x'/>
    <child location='2.3.x'/>
    <child location='2.4.x'/>
    <child location='2.5.x'/>
    <child location='2.6.x'/>
    <child location='2.7.x'/>
  </children>
</repository>
